mml_sql/__init__.py
mml_sql/activate.py
mml_sql/configs/__init__.py
mml_sql/configs/hpo/sql.yaml
mml_sql-0.3.0.dist-info/LICENSE.txt
mml_sql-0.3.0.dist-info/METADATA
mml_sql-0.3.0.dist-info/WHEEL
mml_sql-0.3.0.dist-info/entry_points.txt
mml_sql-0.3.0.dist-info/top_level.txt
mml_sql-0.3.0.dist-info/RECORD
